LICENSE
MANIFEST.in
README.rst
setup.py
pylokit/__init__.py
pylokit/lokit.py
pylokit/lokitconv.py
pylokit/tests.py
pylokit.egg-info/PKG-INFO
pylokit.egg-info/SOURCES.txt
pylokit.egg-info/dependency_links.txt
pylokit.egg-info/not-zip-safe
pylokit.egg-info/requires.txt
pylokit.egg-info/top_level.txt
pylokit/tests/foo.doc