Metadata-Version: 1.1
Name: pylokit
Version: 0.8.1
Summary: Python CFFI wrapper for LibreOfficeKit
Home-page: https://github.com/xrmx/pylokit
Author: Riccardo Magliocchetti
Author-email: riccardo.magliocchetti@gmail.com
License: MPL 2.0
Platform: OS Independent
Classifier: Environment :: Console
Classifier: Intended Audience :: Developers
Classifier: Intended Audience :: System Administrators
Classifier: License :: OSI Approved :: Mozilla Public License 2.0 (MPL 2.0)
Classifier: Operating System :: OS Independent
Classifier: Programming Language :: Python
Classifier: Topic :: Software Development :: Libraries :: Python Modules
Classifier: Topic :: Office/Business :: Office Suites
